MANIFEST.in
README.rst
setup.cfg
setup.py
django_nmrpro/__init__.py
django_nmrpro/admin.py
django_nmrpro/encoder.py
django_nmrpro/exceptions.py
django_nmrpro/models.py
django_nmrpro/session.py
django_nmrpro/tasks.py
django_nmrpro/urls.py
django_nmrpro/views.py
django_nmrpro.egg-info/PKG-INFO
django_nmrpro.egg-info/SOURCES.txt
django_nmrpro.egg-info/dependency_links.txt
django_nmrpro.egg-info/pbr.json
django_nmrpro.egg-info/requires.txt
django_nmrpro.egg-info/top_level.txt
django_nmrpro/migrations/0001_initial.py
django_nmrpro/migrations/__init__.py
django_nmrpro/static/.DS_Store
django_nmrpro/static/nmrpro/.DS_Store
django_nmrpro/static/nmrpro/d3.v3.min.js
django_nmrpro/static/nmrpro/demo.tar.gz
django_nmrpro/static/nmrpro/specdraw.css
django_nmrpro/static/nmrpro/specdraw.js
django_nmrpro/static/nmrpro/specdraw.min.css
django_nmrpro/static/nmrpro/specdraw.min.js
django_nmrpro/templates/.DS_Store
django_nmrpro/templates/coffees_test.html
django_nmrpro/templates/getSpectrum.html
django_nmrpro/templates/nmrpro_js.html
django_nmrpro/templates/specdraw.html
django_nmrpro/templatetags/__init__.py
django_nmrpro/templatetags/nmrpro.py