Metadata-Version: 1.0
Name: django-nmrpro
Version: 0.2.4
Summary: Django app companion for nmrpro package
Home-page: https://github.com/ahmohamed/django_nmrpro
Author: Ahmed Mohamed
Author-email: mohamed@kuicr.kyoto-u.ac.jp
License: MIT
Keywords: nmr,spectra,multi-dimensional
Platform: any
